onlyuserclient/__init__.py
onlyuserclient/apps.py
onlyuserclient/exceptions.py
onlyuserclient/models.py
onlyuserclient/settings.py
onlyuserclient/viewsets.py
onlyuserclient/api/__init__.py
onlyuserclient/api/base.py
onlyuserclient/api/billing.py
onlyuserclient/api/onlyuser.py
onlyuserclient/decorator/__init__.py
onlyuserclient/decorator/billing.py
onlyuserclient/grpc/__init__.py
onlyuserclient/grpc/billing/__init__.py
onlyuserclient/grpc/billing/counter.py
onlyuserclient/grpc/billing/proto/__init__.py
onlyuserclient/grpc/billing/proto/counter_pb2.py
onlyuserclient/grpc/billing/proto/counter_pb2_grpc.py
onlyuserclient/handler/__init__.py
onlyuserclient/handler/billing.py
onlyuserclient/middleware/__init__.py
onlyuserclient/middleware/billing.py
onlyuserclient/middleware/onlyuser.py
onlyuserclient/rpc/__init__.py
onlyuserclient/serializers/__init__.py
onlyuserclient/serializers/fields.py
onlyuserclient/serializers/serializers.py
onlyuserclient/utils/__init__.py
onlyuserclient/utils/functions.py
onlyuserclient-1.3.2.dist-info/licenses/LICENSE
onlyuserclient-1.3.2.dist-info/METADATA
onlyuserclient-1.3.2.dist-info/WHEEL
onlyuserclient-1.3.2.dist-info/top_level.txt
onlyuserclient-1.3.2.dist-info/RECORD
