Metadata-Version: 2.4
Name: onlyuserclient
Version: 1.3.2
Summary: onlyuser client
Home-page: https://github.com/tangdyy/onlyuserclient
Author: Tang dayong
Author-email: tangdyy@126.com
Classifier: Programming Language :: Python :: 3
Classifier: License :: OSI Approved :: MIT License
Classifier: Operating System :: OS Independent
Requires-Python: >=3.6
License-File: LICENSE
Requires-Dist: django
Requires-Dist: djangorestframework
Requires-Dist: simple-rest-client>=1.1.3
Requires-Dist: django-objectid>=1.0.6
Requires-Dist: grpcio>=1.49.1
Requires-Dist: requests>=2.32.3
Dynamic: author
Dynamic: author-email
Dynamic: classifier
Dynamic: description
Dynamic: description-content-type
Dynamic: home-page
Dynamic: license-file
Dynamic: requires-dist
Dynamic: requires-python
Dynamic: summary
